{
    "id": 168,
    "password": "Free to Copy",
    "name": "Crystalline",
    "author": "Stellarum",
    "creators": [],
    "verifier": "Stellarum",
    "verification": "https://youtu.be/FqWS9ZRxCL0",
    "showcase": "https://youtu.be/FqWS9ZRxCL0",
    "percentToQualify": 100,
    "difficulty": "Easy Demon",    
    "records": [     
        {
          "user": "TheRealCave",
          "link": "https://youtu.be/lVVBzANCUnc",
          "hz": 240,
          "percent": 100
        },
        {
          "user": "RedMurder",
          "link": "https://youtu.be/zAw8Fx-Xi1s",
          "hz": 360,
          "percent": 100
        },
        {
          "user": "StolenBurrito",
          "link": "https://youtu.be/T4BId4ato34",
          "hz": 360,
          "percent": 100
        },
        {
          "user": "Rigel",
          "link": "https://drive.google.com/file/d/1-LXmywzik31YE5GZvbMUfhun_fH-ymc9/view?usp=sharing",
          "hz": 360,
          "percent": 100
        },
       {
          "user": "SAINT NICHOLE",
          "link": "https://youtu.be/FdqtLEhF9WA",
          "hz": 360,
          "percent": 100
       },
       {
          "user": "kasiaUwU",
          "link": "https://youtube.com/live/4h6Gho80CuM?feature=share",
          "hz": 240,
          "percent": 100
     },
      {
          "user": "Enzymerz",
          "link": "https://www.youtube.com/watch?v=rmnmmr0UtTk",
          "hz": 60,
          "percent": 100
     },
      {
          "user": "nebnoob",
          "link": "https://youtu.be/uMaencZZH7I",
          "hz": 360,
          "percent": 100
     },
      {
          "user": "CrabbyCrab101",
          "link": "https://www.youtube.com/watch?v=t_x6pajW79A",
          "hz": 240,
          "percent": 100
     },
      {
          "user": "Dino",
          "link": "https://youtu.be/J4xdJ07muLw",
          "hz": 360,
          "percent": 100
     },
      {
          "user": "Splashy",
          "link": "https://youtu.be/-3BaSGDRWcw",
          "hz": 360,
          "percent": 100
      }
    ]
}
